README.md
setup.py
elist/__init__.py
elist/elist.py
elist/lcseq.py
elist/wfsdig.py
elist.egg-info/PKG-INFO
elist.egg-info/SOURCES.txt
elist.egg-info/dependency_links.txt
elist.egg-info/top_level.txt