Metadata-Version: 1.1
Name: elist
Version: 0.4.63
Summary: handle list,nested list tree
Home-page: https://github.com/ihgazni2/elist
Author: dapeli
Author-email: terryinzaghi@163.com
License: MIT
Platform: UNKNOWN
Classifier: Environment :: Console
Classifier: Environment :: Web Environment
Classifier: Intended Audience :: End Users/Desktop
Classifier: Intended Audience :: Developers
Classifier: Intended Audience :: System Administrators
Classifier: Programming Language :: Python
